backend/__init__.py
backend/app.py
backend/auth.py
backend/config.py
backend/database.py
backend/database_utils.py
backend/dependencies.py
backend/feedback_questions.py
backend/models.py
backend/routes.py
backend/seed.py
backend/utils.py
backupbackup-0.0.6.dist-info/licenses/LICENSE
backupbackup-0.0.6.dist-info/METADATA
backupbackup-0.0.6.dist-info/WHEEL
backupbackup-0.0.6.dist-info/top_level.txt
backupbackup-0.0.6.dist-info/RECORD
