Metadata-Version: 2.4
Name: BackupBackup
Version: 0.0.6
Summary: FastAPI-Endpoints with storeage provisioning
Author-email: LeroyLeroy <admin@backupbackup.ch>
Project-URL: Homepage, https://codeberg.org/LeroyLeroy/BackupBackup
Project-URL: Issues, https://codeberg.org/LeroyLeroy/BackupBackup/issues
Requires-Python: >=3.12
License-File: LICENSE
Requires-Dist: bcrypt>=4.3.0
Requires-Dist: captcha>=0.7.1
Requires-Dist: cryptography>=45.0.5
Requires-Dist: fastapi>=0.116.1
Requires-Dist: httpx>=0.28.1
Requires-Dist: jinja2>=3.1.6
Requires-Dist: passlib>=1.7.4
Requires-Dist: pre-commit>=4.2.0
Requires-Dist: pydantic-settings>=2.10.1
Requires-Dist: pydantic[email]>=2.11.7
Requires-Dist: pyjwt>=2.10.1
Requires-Dist: pytest>=8.4.1
Requires-Dist: python-multipart>=0.0.20
Requires-Dist: redis>=6.2.0
Requires-Dist: schedule>=1.2.2
Requires-Dist: sqlmodel>=0.0.24
Requires-Dist: uvicorn>=0.35.0
Dynamic: license-file
